sooj1n_cli/__init__.py
sooj1n_cli/cil.py
sooj1n_cli-0.1.2.dist-info/METADATA
sooj1n_cli-0.1.2.dist-info/WHEEL
sooj1n_cli-0.1.2.dist-info/entry_points.txt
sooj1n_cli-0.1.2.dist-info/top_level.txt
sooj1n_cli-0.1.2.dist-info/RECORD
