Metadata-Version: 2.1
Name: sooj1n_cli
Version: 0.1.2
Summary: Default template for PDM package
Author-email: sooj1n <sujin19371@gmail.com>
License: MIT
Requires-Python: >=3.9
Requires-Dist: sooj1n-lotto >=0.2.0
